{"gbDKuQgUx702LNS95RyMNg==":"mbr-1.jpg","04sx91A9OFPVfnHsr0CBug==":"mbr-2.jpg","vx1HCfMmqDU+s7Eui2JRdg==":"mbr-3.jpg","KZ9bLk9AH2ZsJ75m1vIHgA==":"mbr.png","Y3vQ9NrQmNgUekrM4H/8nA==":"mbr-3.jpeg","4jMTBEKvtHt4yLp64yJ7rQ==":"mbr-4.jpg","vlgcUSC18u1mj5K5ihrfAw==":"mbr-7.jpg","tTz86reHysGEwhEcX5uwVA==":"mbr-8.jpg","HPvps2PYs2xvCuXnWbZ9Hw==":"mbr-8.jpeg","KF+Wa3qUz9G/nA/BRqWBHw==":"mbr.jpeg","LsH5lvBYKniR4SADVP1NTQ==":"mbr-9.jpeg","xvEZoRtTpRo8PQiyUW4s5Q==":"mbr-10.jpg","IDI+CXQpTCod/TkNrC3CYQ==":"mbr.jpg","X0NkBDGMu+zd4PYMoLSDwA==":"mbr-5.jpg","wX76oSpNBIHut/EW6vVidQ==":"mbr-1.jpeg","kBWcS24dsvzugKxtOJfDkA==":"mbr-10.jpeg","3rzWolLdHQ4Ymjqdx3W4sA==":"13009439-12z-2102.w023.n001.71b.p1.71.jpg","JBFxhaG8I9ccI5kFD5ZPBQ==":"kerfin7-nea-2340.jpg","kg042AEqPtJeVPCzAQoplw==":"jack-b-b10axhklvnq-unsplash.jpeg","2kQI7O4DU2WOm3WVIXVGkw==":"jack-b-b10axhklvnq-unsplash-1.jpeg","kZhQmgkJNMy4NFiNyD6b2A==":"ella-don-lb0kkgf8vrc-unsplash-1.jpeg","CiFeef8f/WZio+afZqDKoA==":"background3.jpeg","g/PNkoqgFuP5LRnbVv/8jQ==":"jack-b-b10axhklvnq-unsplash.jpg","bvlXq9pJBVa0F3PJExJwVQ==":"redragon-logo.png","N2JiwjXCabJ44eO8y5Vlyw==":"logo-mancer-2.png","2QTGdQnbte1KfJLo7uOQ8Q==":"aigo-logo.png","vxgN0cCh+nVY95oGcdSF0g==":"branding-guide-improper-logo-5-225x225.png","596wDO4Xa1mnqcyZeg8owA==":"f1472cd9f017531ed6c575beeeabb368.png","hF8FC0SclNgPVbB9fLCLEA==":"dimm-240pin-png-download-corsair-logo-transparent-png-1000x7505989483-pngfind.png","vp1nhLshpTWVoJbU4VJLbQ==":"26-corsair-logo-png-icon-logo-design.png","HESnrlnkY7PsTZzgelrZQQ==":"cougar-logo-sm.png","YEmI17kTdUSwPtzOT2U9QA==":"1597075754179-1459253196fortrek-logo-h-color-copy.png","BXev/VNaDb4HPMk+gXMVUg==":"fortrek-logo.png","2uJRP4l5kwKauDxxMlNyjg==":"hyperx-logo.png","6Zq3MFBM25e1RSVtM0u/Yw==":"logotipo-parceiro-15.png","/FOO37I/lcnHcBIiiGIvrA==":"hyperx-logo-1.png","8miB0FLMqGPintL8hDNbHQ==":"logitech-logo-14.png","Gog3zQ0mTYfEhv9HuKBwPQ==":"download.png","9sSxE/2xwIM7BpmXJMTkWw==":"logitech-background-png-image.png","RP8zv9okZYc8FyRlK/M7YA==":"logitech-background-png-image-1.png","0dZhW4Mhm/SSLjETKDU3Wg==":"fortrek-logo-1.png","bd+1MeMXLYalmlYE/WLrtw==":"fortrek-logo-2.png","751xyncW7ZDY+lo9FqNErQ==":"fortrek-logo-3.png","weggUy7keWvq4nQNzGqf2A==":"fortrek-logo-4.png","50XTqNO2pDHiXI+J75B3Rg==":"logo-motospeed-vetor-vermelho-9000x9000.png","uenC8ZTotQSH3drJTJDTdA==":"logo-motospeed-vetor-vermelho-1-9000x9000.png","5Uye53ritaP4ZeNWEVuY2A==":"cougar-logo-sm-1.png","lmMfFKpJPIFHnpmA5jLuBQ==":"cougar-logo-sm-2.png","kbAXQKwvllNA9lSrdBRe/Q==":"o-circuito.png","fFI2L/7x7SDW++WI/P6gvg==":"kadyn-pierce-zbnga6zcc8-unsplash.jpg","QHFbf16qVMP1bTTqVdmyZw==":"2054.jpg","j8OyjL8/Ux7OatgCCMeYbQ==":"2023-01-a-11-ago-pc-gamer-aniv16-1450x140.png","tXa4mZ3xDrQHs+f/xd5lbQ==":"900x100-2.png","6E2YWuqbeSrR7bgyY4MykA==":"2023-01-a-11-ago-pc-gamer-aniv16-1-1450x140.png","3bZS2Lp8WVjqEvqVrrjy3g==":"900x100-2.jpg"}